{
  "pools": [
    {
      "rolls": 1,
      "entries": [
        {
          "type": "minecraft:item",
          "name": "cobblemon:rare_candy",
          "weight": 1
        },
        {
          "type": "minecraft:item",
          "name": "minecraft:book",
          "weight": 2,
          "functions": [
            {
              "function": "minecraft:enchant_randomly"
            }
          ]
        },
        {
          "type": "minecraft:item",
          "name": "minecraft:heart_of_the_sea",
          "weight": 2
        },
        {
          "type": "minecraft:item",
          "name": "minecraft:gold_ingot",
          "weight": 4,
          "functions": [
            {
              "function": "minecraft:set_count",
              "count": {
                "min": 3,
                "max": 6
              }
            }
          ]
        },
        {
          "type": "minecraft:item",
          "name": "cobblemon:icy_rock",
          "weight": 6
        },
        {
          "type": "minecraft:item",
          "name": "cobblemon:ice_stone",
          "weight": 6
        },
        {
          "type": "minecraft:item",
          "name": "minecraft:cod",
          "weight": 8,
          "functions": [
            {
              "function": "minecraft:set_count",
              "count": {
                "min": 4,
                "max": 6
              }
            }
          ]
        },
        {
          "type": "minecraft:item",
          "name": "minecraft:salmon",
          "weight": 8,
          "functions": [
            {
              "function": "minecraft:set_count",
              "count": {
                "min": 6,
                "max": 8
              }
            }
          ]
        },
        {
          "type": "minecraft:item",
          "name": "cobblemon:lure_ball",
          "weight": 10,
          "functions": [
            {
              "function": "minecraft:set_count",
              "count": {
                "min": 1,
                "max": 4
              }
            }
          ]
        }
      ]
    }
  ]
}
